speechbox/__init__.py
speechbox/dependency_versions_table.py
speechbox/diarize.py
speechbox/restore.py
speechbox/utils/__init__.py
speechbox/utils/dummy_transformers_and_accelerate_and_scipy_objects.py
speechbox/utils/dummy_transformers_and_torchaudio_and_pyannote_objects.py
speechbox/utils/dummy_transformers_objects.py
speechbox/utils/import_utils.py
speechbox-0.2.1.dist-info/LICENSE
speechbox-0.2.1.dist-info/METADATA
speechbox-0.2.1.dist-info/WHEEL
speechbox-0.2.1.dist-info/top_level.txt
speechbox-0.2.1.dist-info/RECORD
