Metadata-Version: 2.1
Name: speechbox
Version: 0.2.1
Summary: Speechbox
Home-page: https://github.com/huggingface/speechbox
Author: The HuggingFace team
Author-email: patrick@huggingface.co
License: Apache
Keywords: deep learning
Classifier: Development Status :: 5 - Production/Stable
Classifier: Intended Audience :: Developers
Classifier: Intended Audience :: Education
Classifier: Intended Audience :: Science/Research
Classifier: License :: OSI Approved :: Apache Software License
Classifier: Operating System :: OS Independent
Classifier: Programming Language :: Python :: 3
Classifier: Programming Language :: Python :: 3.7
Classifier: Programming Language :: Python :: 3.8
Classifier: Programming Language :: Python :: 3.9
Classifier: Topic :: Scientific/Engineering :: Artificial Intelligence
Requires-Python: >=3.7.0
License-File: LICENSE
Requires-Dist: torch (>=1.9)
Requires-Dist: importlib-metadata
Requires-Dist: filelock
Requires-Dist: numpy
Provides-Extra: dev
Requires-Dist: black (==22.8) ; extra == 'dev'
Requires-Dist: isort (>=5.5.4) ; extra == 'dev'
Requires-Dist: flake8 (>=3.8.3) ; extra == 'dev'
Requires-Dist: transformers (>=4.24.0) ; extra == 'dev'
Requires-Dist: accelerate (>=0.14.0) ; extra == 'dev'
Requires-Dist: datasets (>=2.7.0) ; extra == 'dev'
Requires-Dist: torchaudio ; extra == 'dev'
Requires-Dist: pyannote.audio ; extra == 'dev'
Provides-Extra: quality
Requires-Dist: black (==22.8) ; extra == 'quality'
Requires-Dist: isort (>=5.5.4) ; extra == 'quality'
Requires-Dist: flake8 (>=3.8.3) ; extra == 'quality'
